<?xml version="1.0" encoding="utf-8" ?>
<Patch>          

<!-- CONCEALED -->
                <Operation Class="PatchOperationReplace">
                    <success>Always</success>
                    <xpath>Defs/ThingDef[@Name="BaseArrowSlitTrap"]/designationCategory</xpath>
                    <value>
                        <designationCategory>Ferny_Traps</designationCategory>
                    </value>
                </Operation>
                <Operation Class="PatchOperationReplace">
                    <success>Always</success>
                    <xpath>Defs/ThingDef[defName="PressurePlate"]/designationCategory</xpath>
                    <value>
                        <designationCategory>Ferny_Traps</designationCategory>
                    </value>
                </Operation>

</Patch>
